{
    "themes": {
        "tech_news": {
            "name": "科技新闻",
            "description": "科技资讯类节目",
            "voice": "onyx",
            "voice_style": "专业、稳重",
            "bgm": "electronic_pulse.mp3",
            "scripts": [
                {
                    "id": "opening",
                    "text": "各位观众朋友们大家好，欢迎收看今天的AI主播台科技新闻节目。我是您的AI主播，现在为您播报今日科技要闻。",
                    "duration": 10
                },
                {
                    "id": "news_1",
                    "text": "首先关注人工智能领域的重大突破。据报道，新一代大语言模型的推理速度提升了十倍，这将极大地推动AI应用的普及和发展。",
                    "duration": 12
                },
                {
                    "id": "news_2",
                    "text": "在量子计算领域，科研人员取得了里程碑式的进展，量子计算机正式进入实用化阶段，有望在未来五年内改变现有的计算范式。",
                    "duration": 12
                },
                {
                    "id": "news_3",
                    "text": "芯片产业方面，国产替代进程持续加速，多款自主研发的高性能芯片已经实现量产，标志着我国半导体产业迈入新纪元。",
                    "duration": 12
                },
                {
                    "id": "news_4",
                    "text": "自动驾驶技术也传来好消息，L4级别自动驾驶已经在多个城市开展商业化运营，智能出行时代正在加速到来。",
                    "duration": 12
                },
                {
                    "id": "closing",
                    "text": "以上是今天的科技新闻播报。感谢您的收看，我们下期节目再见。",
                    "duration": 6
                }
            ]
        },
        "morning_news": {
            "name": "早间新闻",
            "description": "轻松愉快的早间播报",
            "voice": "nova",
            "voice_style": "活力、亲切",
            "bgm": "bright_upbeat.mp3",
            "scripts": [
                {
                    "id": "opening",
                    "text": "早上好！新的一天开始了，欢迎收听AI主播台早间新闻。让我们用最新资讯开启元气满满的一天！",
                    "duration": 8
                },
                {
                    "id": "weather",
                    "text": "首先来关注今天的天气情况。今天阳光明媚，气温适宜，非常适合户外活动，记得做好防晒哦。",
                    "duration": 10
                },
                {
                    "id": "news_1",
                    "text": "健康生活小贴士：研究表明，每天保持适量运动和充足睡眠，可以显著提高工作效率和生活质量。",
                    "duration": 10
                },
                {
                    "id": "news_2",
                    "text": "教育领域传来好消息，人工智能辅助教学系统已在全国多所学校试点应用，个性化学习正在成为现实。",
                    "duration": 10
                },
                {
                    "id": "closing",
                    "text": "祝大家今天工作顺利，心情愉快！我们明天早上再见！",
                    "duration": 6
                }
            ]
        },
        "evening_news": {
            "name": "晚间新闻",
            "description": "深度报道晚间新闻",
            "voice": "echo",
            "voice_style": "沉稳、有深度",
            "bgm": "piano_ambient.mp3",
            "scripts": [
                {
                    "id": "opening",
                    "text": "晚上好，欢迎收看AI主播台晚间新闻。在这个宁静的夜晚，让我们为您梳理今天的重要新闻事件。",
                    "duration": 8
                },
                {
                    "id": "headline",
                    "text": "今日头条：国家科技创新战略持续推进，多项重大科技项目取得突破性进展。",
                    "duration": 10
                },
                {
                    "id": "news_1",
                    "text": "经济方面，数字经济持续蓬勃发展，新业态新模式不断涌现，为经济增长注入强劲动力。",
                    "duration": 12
                },
                {
                    "id": "news_2",
                    "text": "社会民生领域，医疗健康服务不断优化，远程医疗让优质医疗资源惠及更多群众。",
                    "duration": 12
                },
                {
                    "id": "news_3",
                    "text": "环保领域，碳中和目标稳步推进，清洁能源占比持续提升，绿色发展理念深入人心。",
                    "duration": 12
                },
                {
                    "id": "closing",
                    "text": "感谢您收看今天的晚间新闻。祝您晚安，好梦。",
                    "duration": 6
                }
            ]
        },
        "finance_report": {
            "name": "财经报道",
            "description": "专业财经资讯",
            "voice": "fable",
            "voice_style": "专业、权威",
            "bgm": "deep_bass.mp3",
            "scripts": [
                {
                    "id": "opening",
                    "text": "欢迎收看AI主播台财经报道。我是您的财经主播，现在为您播报今日财经要闻。",
                    "duration": 8
                },
                {
                    "id": "market",
                    "text": "股市方面，今日A股市场整体呈现震荡走势，科技板块表现活跃，新能源概念股涨幅居前。",
                    "duration": 12
                },
                {
                    "id": "news_1",
                    "text": "数字经济成为经济增长新引擎，数字化转型正在深刻改变各行各业的发展模式。",
                    "duration": 12
                },
                {
                    "id": "news_2",
                    "text": "跨境贸易持续升温，电商平台海外业务快速增长，中国品牌正在加速走向世界。",
                    "duration": 12
                },
                {
                    "id": "closing",
                    "text": "以上是今天的财经报道。投资有风险，入市需谨慎。感谢您的收看。",
                    "duration": 8
                }
            ]
        },
        "entertainment": {
            "name": "娱乐快讯",
            "description": "轻松娱乐内容",
            "voice": "shimmer",
            "voice_style": "活泼、有趣",
            "bgm": "lofi_chill.mp3",
            "scripts": [
                {
                    "id": "opening",
                    "text": "哈喽大家好！欢迎来到AI主播台娱乐快讯，我是你们的主播，今天又有什么有趣的事情呢？一起来看看吧！",
                    "duration": 8
                },
                {
                    "id": "news_1",
                    "text": "文化娱乐方面，虚拟演唱会正在成为新潮流，越来越多的艺人开始尝试元宇宙演出，让粉丝足不出户就能享受顶级视听盛宴。",
                    "duration": 12
                },
                {
                    "id": "news_2",
                    "text": "游戏产业持续火热，国产游戏在国际市场表现亮眼，多款原创游戏获得全球玩家好评。",
                    "duration": 12
                },
                {
                    "id": "news_3",
                    "text": "社交媒体新趋势：短视频内容创作进入专业化时代，优质内容创作者迎来更多发展机遇。",
                    "duration": 12
                },
                {
                    "id": "closing",
                    "text": "今天的娱乐快讯就到这里，希望大家每天都能开开心心！我们下期再见啦！",
                    "duration": 6
                }
            ]
        },
        "ai_knowledge": {
            "name": "AI知识讲堂",
            "description": "人工智能科普节目",
            "voice": "alloy",
            "voice_style": "清晰、易懂",
            "bgm": "ambient_dream.mp3",
            "scripts": [
                {
                    "id": "opening",
                    "text": "欢迎来到AI知识讲堂。在这个节目中，我们将带您了解人工智能的前沿技术和应用。",
                    "duration": 8
                },
                {
                    "id": "topic_intro",
                    "text": "今天我们要聊的话题是：大语言模型是如何理解和生成人类语言的？",
                    "duration": 8
                },
                {
                    "id": "content_1",
                    "text": "大语言模型通过海量文本数据训练，学习语言的规律和知识。它能够理解上下文语境，生成连贯、有逻辑的回复。",
                    "duration": 15
                },
                {
                    "id": "content_2",
                    "text": "这些模型的应用场景非常广泛，包括智能客服、内容创作、代码辅助等，正在深刻改变我们的工作方式。",
                    "duration": 12
                },
                {
                    "id": "closing",
                    "text": "今天的AI知识讲堂就到这里，希望对您有所帮助。我们下期再见！",
                    "duration": 6
                }
            ]
        }
    },
    "voices": {
        "alloy": {
            "name": "合金",
            "style": "中性、清晰",
            "gender": "中性",
            "suitable": ["科普", "教学"]
        },
        "echo": {
            "name": "回声",
            "style": "男性、沉稳",
            "gender": "男",
            "suitable": ["新闻", "深度报道"]
        },
        "fable": {
            "name": "寓言",
            "style": "英式、优雅",
            "gender": "男",
            "suitable": ["财经", "纪录片"]
        },
        "onyx": {
            "name": "玛瑙",
            "style": "男性、深沉",
            "gender": "男",
            "suitable": ["新闻", "科技"]
        },
        "nova": {
            "name": "新星",
            "style": "女性、活力",
            "gender": "女",
            "suitable": ["早间", "娱乐"]
        },
        "shimmer": {
            "name": "微光",
            "style": "女性、温暖",
            "gender": "女",
            "suitable": ["娱乐", "生活"]
        }
    },
    "schedule": {
        "morning": {
            "time_range": "06:00-12:00",
            "theme": "morning_news"
        },
        "afternoon": {
            "time_range": "12:00-18:00",
            "theme": "tech_news"
        },
        "evening": {
            "time_range": "18:00-22:00",
            "theme": "evening_news"
        },
        "night": {
            "time_range": "22:00-06:00",
            "theme": "ai_knowledge"
        }
    },
    "ticker_content": {
        "tech_news": [
            "AI技术突破：大模型推理速度提升10倍",
            "量子计算进入实用阶段：商业化应用加速",
            "芯片国产替代：自主研发取得重大进展",
            "自动驾驶L4时代：商业化运营启动",
            "元宇宙应用落地：虚拟与现实深度融合"
        ],
        "morning_news": [
            "早安寄语：新的一天，新的开始",
            "健康生活：坚持运动，保持活力",
            "职场技巧：高效工作的秘诀分享",
            "科技前沿：AI改变生活的100种方式",
            "教育创新：智能学习新时代来临"
        ],
        "evening_news": [
            "晚间头条：今日要闻回顾",
            "经济观察：数字经济发展态势良好",
            "民生关注：医疗健康服务持续优化",
            "环保先锋：碳中和目标稳步推进",
            "文化视点：数字文化产业蓬勃发展"
        ],
        "finance_report": [
            "股市动态：科技板块表现活跃",
            "数字经济：新业态新模式涌现",
            "跨境贸易：电商平台海外增长",
            "投资风向：科技创新受关注",
            "市场分析：新兴产业前景广阔"
        ],
        "entertainment": [
            "虚拟演唱会：元宇宙娱乐新体验",
            "游戏产业：国产游戏走向世界",
            "短视频热潮：内容创作专业化",
            "直播电商：新零售模式兴起",
            "影视动态：优质内容持续产出"
        ],
        "ai_knowledge": [
            "AI科普：什么是大语言模型",
            "机器学习：让机器学会思考",
            "深度学习：神经网络的力量",
            "计算机视觉：机器如何看世界",
            "自然语言处理：机器如何理解人类语言"
        ]
    }
}
